graph_sign_and_verify_c4gai/__init__.py
graph_sign_and_verify_c4gai/example.py
graph_sign_and_verify_c4gai/graphsignature.py
graph_sign_and_verify_c4gai/order-1.nt.sha
graph_sign_and_verify_c4gai/rdf_canonicalization.py
graph_sign_and_verify_c4gai/sign.py
graph_sign_and_verify_c4gai/tmp/normalized_nt-sort.nt
graph_sign_and_verify_c4gai/tmp/normalized_nt.nt
graph_sign_and_verify_c4gai-0.0.1.dist-info/LICENSE
graph_sign_and_verify_c4gai-0.0.1.dist-info/METADATA
graph_sign_and_verify_c4gai-0.0.1.dist-info/WHEEL
graph_sign_and_verify_c4gai-0.0.1.dist-info/RECORD
