Metadata-Version: 2.1
Name: graph-sign-and-verify-c4gai
Version: 0.0.1
Summary: Sign and verify your awesome Knowledge Graphs with eccenca Corporate Memory :-)
License: Apache-2.0
Author: eccenca GmbH
Author-email: magnus.knuth@eccenca.com
Requires-Python: >=3.11,<4
Classifier: Development Status :: 4 - Beta
Classifier: License :: OSI Approved :: Apache Software License
Classifier: Programming Language :: Python :: 3
Classifier: Programming Language :: Python :: 3.11
Classifier: Programming Language :: Python :: 3.12
Requires-Dist: cryptography (>=43.0.3,<44.0.0)
